LICENSE
MANIFEST.in
README.md
VERSION
setup.py
panther_okta/__init__.py
panther_okta/_shared.py
panther_okta/py.typed
panther_okta/sample_logs.py
panther_okta.egg-info/PKG-INFO
panther_okta.egg-info/SOURCES.txt
panther_okta.egg-info/dependency_links.txt
panther_okta.egg-info/requires.txt
panther_okta.egg-info/top_level.txt
panther_okta/queries/__init__.py
panther_okta/queries/all_queries.py
panther_okta/rules/__init__.py
panther_okta/rules/admin_actions.py
panther_okta/rules/api_keys.py
panther_okta/rules/brute_force_login.py
panther_okta/rules/improbable_access.py
panther_okta/rules/support_actions.py
tests/__init__.py
tests/test_module.py
tests/test_queries.py
tests/test_rules_admin_actions.py
tests/test_rules_api_keys.py
tests/test_rules_improbable_access.py
tests/test_rules_support_actions.py